{
  "db_name": "PostgreSQL",
  "query": "SELECT COUNT(*)\n                       FROM LeaderboardSolve\n                       WHERE puzzle_id = $1\n                           AND blind = $2\n                           AND uses_filters = $3\n                           AND uses_macros = $4\n                           AND id <> $5\n                           AND speed_cs IS NOT NULL\n                       LIMIT 1\n                   ",
  "describe": {
    "columns": [
      {
        "ordinal": 0,
        "name": "count",
        "type_info": "Int8"
      }
    ],
    "parameters": {
      "Left": [
        "Int4",
        "Bool",
        "Bool",
        "Bool",
        "Int4"
      ]
    },
    "nullable": [
      null
    ]
  },
  "hash": "aef95fde869c9a832ea415c5257e67a41cd54e2a7138add6494a29f664fef33c"
}
